compnet/__about__.py
compnet/__init__.py
compnet/algo.py
compnet/res/__init__.py
compnet/res/by-nc-sa.eu.svg
compnet/tests/__init__.py
compnet/tests/test_all.py
compnet/tests/tests.py
compnet-0.8.8.dist-info/licenses/LICENSE.md
compnet-0.8.8.dist-info/METADATA
compnet-0.8.8.dist-info/WHEEL
compnet-0.8.8.dist-info/top_level.txt
compnet-0.8.8.dist-info/RECORD
