Metadata-Version: 2.4
Name: compnet
Version: 0.8.8
Summary: A package for market compression of network data.
Home-page: https://github.com/LucaMingarelli/compnet
Author: Luca Mingarelli
Author-email: lucamingarelli@me.com
License: CC BY-NC-SA 4.0
Classifier: Programming Language :: Python :: 3
Classifier: License :: OSI Approved :: MIT License
Classifier: Operating System :: OS Independent
Requires-Python: >=3.6
License-File: LICENSE.md
Requires-Dist: numpy
Requires-Dist: pandas
Requires-Dist: numba
Requires-Dist: scipy
Requires-Dist: tqdm
Requires-Dist: tabulate
Requires-Dist: networkx
Requires-Dist: duckdb
Dynamic: author
Dynamic: author-email
Dynamic: classifier
Dynamic: description
Dynamic: description-content-type
Dynamic: home-page
Dynamic: license
Dynamic: license-file
Dynamic: requires-dist
Dynamic: requires-python
Dynamic: summary
